jupyterlab_simpledark/__init__.py
jupyterlab_simpledark-1.0.2.data/data/share/jupyter/labextensions/jupyterlab-simpledark/package.json
jupyterlab_simpledark-1.0.2.data/data/share/jupyter/labextensions/jupyterlab-simpledark/static/496.825d7cdd9aa39b56546f.js
jupyterlab_simpledark-1.0.2.data/data/share/jupyter/labextensions/jupyterlab-simpledark/static/remoteEntry.2823dfbe182a71ee204d.js
jupyterlab_simpledark-1.0.2.data/data/share/jupyter/labextensions/jupyterlab-simpledark/static/style.js
jupyterlab_simpledark-1.0.2.data/data/share/jupyter/labextensions/jupyterlab-simpledark/static/third-party-licenses.json
jupyterlab_simpledark-1.0.2.data/data/share/jupyter/labextensions/jupyterlab-simpledark/themes/jupyterlab-simpledark/index.css
jupyterlab_simpledark-1.0.2.data/data/share/jupyter/labextensions/jupyterlab-simpledark/themes/jupyterlab-simpledark/index.js
jupyterlab_simpledark-1.0.2.data/data/share/jupyter/labextensions/jupyterlab-simpledark/install.json
jupyterlab_simpledark-1.0.2.dist-info/METADATA
jupyterlab_simpledark-1.0.2.dist-info/WHEEL
jupyterlab_simpledark-1.0.2.dist-info/licenses/LICENSE
jupyterlab_simpledark-1.0.2.dist-info/RECORD
