Metadata-Version: 2.1
Name: jupyterlab_simpledark
Version: 1.0.2
Summary: A (growing) dark theme collection for JupyterLab.
Project-URL: Homepage, https://github.com/ericmiguel/jupyterlab-simpledark
Project-URL: Bug Tracker, https://github.com/ericmiguel/jupyterlab-simpledark/issues
Project-URL: Repository, https://github.com/ericmiguel/jupyterlab-simpledark.git
Author-email: Eric Miguel <eric.mrib@gmail.com>
License: BSD 3-Clause License
License-File: LICENSE
Classifier: Framework :: Jupyter
Classifier: Framework :: Jupyter :: JupyterLab
Classifier: Framework :: Jupyter :: JupyterLab :: 4
Classifier: Framework :: Jupyter :: JupyterLab :: Extensions
Classifier: Framework :: Jupyter :: JupyterLab :: Extensions :: Prebuilt
Classifier: License :: OSI Approved :: BSD License
Classifier: Programming Language :: Python
Classifier: Programming Language :: Python :: 3
Classifier: Programming Language :: Python :: 3.8
Classifier: Programming Language :: Python :: 3.9
Classifier: Programming Language :: Python :: 3.10
Classifier: Programming Language :: Python :: 3.11
Classifier: Programming Language :: Python :: 3.12
Requires-Python: >=3.8
